setup.py
sputr/__init__.py
sputr/__main__.py
sputr/cli.py
sputr/click_cli.py
sputr/config.py
sputr/runner.py
sputr/sputr.py
sputr.egg-info/PKG-INFO
sputr.egg-info/SOURCES.txt
sputr.egg-info/dependency_links.txt
sputr.egg-info/entry_points.txt
sputr.egg-info/requires.txt
sputr.egg-info/top_level.txt